datetimes/__init__.py
datetimes/leaks.py
datetimes/admin/__init__.py
datetimes/log/__init__.py
datetimes/paid/__init__.py
datetimes/paid/admin.py
datetimes/paid/config.py
datetimes/paid/database.py
datetimes/paid/import_export.py
datetimes/paid/main.py
datetimes/paid/paid_config.py
datetimes/paid/premium.py
pysmongo-1.0.0.dist-info/LICENSE
pysmongo-1.0.0.dist-info/METADATA
pysmongo-1.0.0.dist-info/WHEEL
pysmongo-1.0.0.dist-info/top_level.txt
pysmongo-1.0.0.dist-info/RECORD
