Metadata-Version: 2.1
Name: pysmongo
Version: 1.0.0
Summary: A small Python MongoDB Document-Based access engine
Home-page: https://github.com/DKBOTZNETWORK
Author: DKBOTZ
License: GNU AFFERO GENERAL PUBLIC LICENSE (v3)
Classifier: Programming Language :: Python :: 3
Classifier: Programming Language :: Python :: 3.6
Classifier: Programming Language :: Python :: 3.7
Classifier: Programming Language :: Python :: 3.8
Classifier: Programming Language :: Python :: 3.9
Classifier: License :: OSI Approved :: GNU General Public License v3 (GPLv3)
Classifier: Operating System :: OS Independent
Requires-Python: >=3.6
License-File: LICENSE
Requires-Dist: requests
Requires-Dist: pymongo
Requires-Dist: aiofiles
Requires-Dist: aiohttp
Requires-Dist: motor
Requires-Dist: pyromod
